src/__init__.py
src/analyzers/__init__.py
src/analyzers/ast_utils.py
src/analyzers/typescript_base.py
src/api.py
src/cli/__init__.py
src/cli/__main__.py
src/cli/config.py
src/cli/config_merge.py
src/cli/linters/__init__.py
src/cli/linters/code_patterns.py
src/cli/linters/code_smells.py
src/cli/linters/documentation.py
src/cli/linters/performance.py
src/cli/linters/shared.py
src/cli/linters/structure.py
src/cli/linters/structure_quality.py
src/cli/main.py
src/cli/utils.py
src/cli_main.py
src/config.py
src/core/__init__.py
src/core/base.py
src/core/cli_utils.py
src/core/config_parser.py
src/core/constants.py
src/core/linter_utils.py
src/core/registry.py
src/core/rule_discovery.py
src/core/types.py
src/core/violation_builder.py
src/core/violation_utils.py
src/formatters/__init__.py
src/formatters/sarif.py
src/linter_config/__init__.py
src/linter_config/directive_markers.py
src/linter_config/ignore.py
src/linter_config/loader.py
src/linter_config/pattern_utils.py
src/linter_config/rule_matcher.py
src/linters/__init__.py
src/linters/collection_pipeline/__init__.py
src/linters/collection_pipeline/any_all_analyzer.py
src/linters/collection_pipeline/ast_utils.py
src/linters/collection_pipeline/config.py
src/linters/collection_pipeline/continue_analyzer.py
src/linters/collection_pipeline/detector.py
src/linters/collection_pipeline/filter_map_analyzer.py
src/linters/collection_pipeline/linter.py
src/linters/collection_pipeline/suggestion_builder.py
src/linters/dry/__init__.py
src/linters/dry/base_token_analyzer.py
src/linters/dry/block_filter.py
src/linters/dry/block_grouper.py
src/linters/dry/cache.py
src/linters/dry/cache_query.py
src/linters/dry/config.py
src/linters/dry/config_loader.py
src/linters/dry/constant.py
src/linters/dry/constant_matcher.py
src/linters/dry/constant_violation_builder.py
src/linters/dry/deduplicator.py
src/linters/dry/duplicate_storage.py
src/linters/dry/file_analyzer.py
src/linters/dry/inline_ignore.py
src/linters/dry/linter.py
thailint-0.15.0.dist-info/METADATA
thailint-0.15.0.dist-info/WHEEL
thailint-0.15.0.dist-info/entry_points.txt
thailint-0.15.0.dist-info/licenses/LICENSE
thailint-0.15.0.dist-info/RECORD
