Metadata-Version: 2.4
Name: thailint
Version: 0.15.0
Summary: The AI Linter - Enterprise-grade linting and governance for AI-generated code across multiple languages
License: MIT
License-File: LICENSE
Keywords: linter,ai,code-quality,static-analysis,file-placement,governance,multi-language,cli,docker,python,performance,typescript
Author: Steve Jackson
Requires-Python: >=3.11,<4.0
Classifier: Development Status :: 4 - Beta
Classifier: Environment :: Console
Classifier: Intended Audience :: Developers
Classifier: License :: OSI Approved :: MIT License
Classifier: Operating System :: OS Independent
Classifier: Programming Language :: Python :: 3
Classifier: Programming Language :: Python :: 3.11
Classifier: Programming Language :: Python :: 3.12
Classifier: Programming Language :: Python :: 3.13
Classifier: Programming Language :: Python :: 3.14
Classifier: Programming Language :: Python :: 3 :: Only
Classifier: Topic :: Software Development :: Libraries :: Python Modules
Classifier: Topic :: Software Development :: Quality Assurance
Classifier: Topic :: Software Development :: Testing
Classifier: Topic :: Utilities
Classifier: Typing :: Typed
Requires-Dist: click (>=8.1.0,<9.0.0)
Requires-Dist: pyprojroot (>=0.3.0,<0.4.0)
Requires-Dist: pyyaml (>=6.0,<7.0)
Requires-Dist: tree-sitter (>=0.25.2,<0.26.0)
Requires-Dist: tree-sitter-typescript (>=0.23.2,<0.24.0)
Project-URL: Documentation, https://thai-lint.readthedocs.io/
Project-URL: Homepage, https://github.com/be-wise-be-kind/thai-lint
Project-URL: Repository, https://github.com/be-wise-be-kind/thai-lint
